oas_patch/__init__.py
oas_patch/bundle_manager.py
oas_patch/cli_utils.py
oas_patch/environment_manager.py
oas_patch/file_utils.py
oas_patch/oas_patcher_cli.py
oas_patch/overlay.py
oas_patch/overlay_diff.py
oas_patch/template_engine.py
oas_patch/validator.py
oas_patch/schema/__init__.py
oas_patch/schema/overlay_schema_1.0.0.yml
oas_patch-0.5.6.dist-info/licenses/LICENSE
oas_patch-0.5.6.dist-info/METADATA
oas_patch-0.5.6.dist-info/WHEEL
oas_patch-0.5.6.dist-info/entry_points.txt
oas_patch-0.5.6.dist-info/top_level.txt
oas_patch-0.5.6.dist-info/RECORD
