Metadata-Version: 2.4
Name: oas_patch
Version: 0.5.6
Summary: A complete cli/lib to apply overlays to OpenAPI documents, powering your ci/cd and API lifecycle
Home-page: https://github.com/mcroissant/oas_patcher
Author: Matthieu Croissant
Classifier: Programming Language :: Python :: 3
License-File: LICENSE
Requires-Dist: PyYAML>=6.0
Requires-Dist: jsonpath-ng>=1.7.0
Requires-Dist: jsonschema>=4.23.0
Requires-Dist: deepdiff>=8.4.2
Requires-Dist: Jinja2>=3.1.0
Requires-Dist: rich>=13.0.0
Requires-Dist: click>=8.0.0
Dynamic: author
Dynamic: classifier
Dynamic: description
Dynamic: description-content-type
Dynamic: home-page
Dynamic: license-file
Dynamic: requires-dist
Dynamic: summary
